[
  {
    "variation": "default-slice",
    "name": "Default slice",
    "slice_type": "hero_slice",
    "items": [],
    "primary": {
      "BackgroundImage": {
        "dimensions": {
          "width": 400,
          "height": 400
        },
        "alt": "Placeholder image",
        "copyright": null,
        "url": "https://images.unsplash.com/photo-1587840171670-8b850147754e?w=400&h=400&fit=crop"
      },
      "HeroText": [
        {
          "type": "paragraph",
          "text": "Ut reprehenderit sit do cupidatat aliquip occaecat quis. Pariatur magna magna sunt sunt Lorem.",
          "spans": []
        }
      ]
    }
  }
]